a1facts/knowledge_base.py
a1facts/enrichment/__init__.py
a1facts/enrichment/knowledge_acquirer.py
a1facts/enrichment/knowledge_source.py
a1facts/enrichment/function_knowledge_source/knowledge_source.py
a1facts/enrichment/function_knowledge_source/query_agent.py
a1facts/enrichment/mcp_knowledge_source/knowledge_source.py
a1facts/graph/__init__.py
a1facts/graph/graph_database.py
a1facts/graph/knowledge_graph.py
a1facts/graph/neo4j_graph_database.py
a1facts/graph/networkx_graph_database.py
a1facts/graph/query_agent.py
a1facts/graph/query_rewrite_agent.py
a1facts/graph/update_agent.py
a1facts/ontology/__init__.py
a1facts/ontology/entity_class.py
a1facts/ontology/knowledge_ontology.py
a1facts/ontology/ontology_rewrite_agent.py
a1facts/ontology/property.py
a1facts/ontology/rdfs_entity.py
a1facts/ontology/rdfs_property.py
a1facts/ontology/rdfs_relationship.py
a1facts/ontology/relationship_class.py
a1facts/utils/__init__.py
a1facts/utils/aliases.py
a1facts/utils/logger.py
a1facts/utils/modelconfig.py
a1facts/utils/telemetry.py
a1facts/utils/timer.py
a1facts-0.2.6.dist-info/licenses/LICENSE
a1facts-0.2.6.dist-info/METADATA
a1facts-0.2.6.dist-info/WHEEL
a1facts-0.2.6.dist-info/top_level.txt
a1facts-0.2.6.dist-info/RECORD
