Metadata-Version: 2.4
Name: a1facts
Version: 0.2.6
Summary: a1facts - precise knowledge for AI agents
Author-email: Shadi Copty <shadi@a1facts.ai>
License:                        Apache License
Project-URL: Homepage, https://github.com/shadi-fsai/a1facts
Project-URL: Issues, https://github.com/shadi-fsai/a1facts/issues
Requires-Python: >=3.13
License-File: LICENSE
Requires-Dist: agno>=1.8.0
Requires-Dist: chromadb>=1.0.13
Requires-Dist: colored>=2.3.1
Requires-Dist: exa-py>=1.15.3
Requires-Dist: mcp>=1.13.1
Requires-Dist: neo4j>=5.28.2
Requires-Dist: nest-asyncio>=1.6.0
Requires-Dist: networkx>=3.5
Requires-Dist: posthog>=6.7.1
Requires-Dist: pytest>=8.4.2
Requires-Dist: pytest-docker>=3.2.3
Requires-Dist: rdflib>=7.2.1
Requires-Dist: sentence-transformers>=5.1.1
Requires-Dist: spacy>=3.8.7
Requires-Dist: thefuzz>=0.22.1
Requires-Dist: yfinance>=0.2.65
Provides-Extra: dev
Requires-Dist: pytest>=8.4.2; extra == "dev"
Dynamic: license-file
